magic_patch/__init__.py
magic_patch-0.0.2.dist-info/LICENSE
magic_patch-0.0.2.dist-info/METADATA
magic_patch-0.0.2.dist-info/WHEEL
magic_patch-0.0.2.dist-info/top_level.txt
magic_patch-0.0.2.dist-info/RECORD
