Metadata-Version: 2.1
Name: magic-patch
Version: 0.0.2
Summary: The magic_patch is a simple library that provides the ability to patch an object in different scopes at once. Now you can patch objects easily like magic.
Home-page: https://github.com/dart-neitro/magic_patch
Author: Konstantin Neitro
Author-email: neitro88@gmail.com
License: UNKNOWN
Platform: UNKNOWN
Classifier: Programming Language :: Python :: 3
Classifier: License :: OSI Approved :: MIT License
Classifier: Operating System :: OS Independent
Requires-Python: >=3.5
